[
    {
        "first_name":"MARK GILSON",
        "middle_name":"PECANA",
        "last_name":"GREGORIO",
        "suffix":"",
        "uniq_id":"1"
    },
    {
        "first_name":"MARK ANTHONY",
        "middle_name":"ESPELA",
        "last_name":"OLIVARES",
        "suffix":"",
        "uniq_id":"2"
    },
    {
        "first_name":"JOHN JEYMAR",
        "middle_name":"",
        "last_name":"JORDAN",
        "suffix":"",
        "uniq_id":"3"
    },
    {
        "first_name":"ANGELO",
        "middle_name":"ROASA",
        "last_name":"AGARCIO",
        "suffix":"",
        "uniq_id":"4"
    },
    {
        "first_name":"JOHN BILEE",
        "middle_name":"",
        "last_name":"TALPLACIDO",
        "suffix":"SR",
        "uniq_id":"5"
    }
]